log_search_pkg/__init__.py
log_search_pkg/main.py
pkg_log_search-0.0.1.dist-info/licenses/LICENCE
pkg_log_search-0.0.1.dist-info/METADATA
pkg_log_search-0.0.1.dist-info/WHEEL
pkg_log_search-0.0.1.dist-info/entry_points.txt
pkg_log_search-0.0.1.dist-info/top_level.txt
pkg_log_search-0.0.1.dist-info/RECORD
