Metadata-Version: 2.4
Name: pkg-log-search
Version: 0.0.1
Summary: Command-line tool to filter structured log files by date, level, module, or message pattern
Author-email: Saad Khalmadani <saad.khalmadani@gmail.com>
License-Expression: MIT
Classifier: Programming Language :: Python :: 3
Classifier: Operating System :: OS Independent
Requires-Python: >=3.13
License-File: LICENCE
Dynamic: license-file
